ocpiupdate/v2_4_7_updater.py
ocpiupdater-0.1.0.dist-info/METADATA
ocpiupdater-0.1.0.dist-info/WHEEL
ocpiupdater-0.1.0.dist-info/top_level.txt
ocpiupdater-0.1.0.dist-info/RECORD
