Metadata-Version: 2.1
Name: ocpiupdater
Version: 0.1.0
Summary: An updater for OpenCPI Projects
Requires-Python: >=3.8
